{
  "key": "mnp-12-1-PBR-SCN",
  "name": "WK1 PBR @ SCN",
  "type": "manual",
  "week": "1",
  "round": 4,
  "create_at": 1568051823776,
  "date": "09/09/2019",
  "state": "complete",
  "venue": {
    "key": "FCH",
    "name": "Full Tilt Capitol Hill",
    "machines": [
      "Tron",
      "WhoDunnit",
      "GOT",
      "RFM",
      "RollerGames",
      "TSPP",
      "StarWarsE1",
      "BDK"
    ]
  },
  "away": {
    "name": "Point Breakers",
    "key": "PBR",
    "captains": [
      {
        "key": "98326b585dcf615cb04751c475b9c754240a84bd",
        "name": "Hayden McCabe"
      },
      {
        "key": "7ee8412002913a652b06f39c31474dcf2c18cdf6",
        "name": "Clayton Stetz"
      }
    ],
    "lineup": [
      {
        "key": "14ca720acc6a110a0aede4417bdccbd293700d49",
        "name": "Blake Mitchell",
        "sub": false,
        "num_played": 3,
        "IPR": 5
      },
      {
        "key": "ace784f327f66c086f5246dbb25e7f2eed9a0c68",
        "name": "Brian Hyder",
        "sub": false,
        "num_played": 3,
        "IPR": 4
      },
      {
        "key": "7ee8412002913a652b06f39c31474dcf2c18cdf6",
        "name": "Clayton Stetz",
        "sub": false,
        "num_played": 3,
        "IPR": 3
      },
      {
        "key": "98326b585dcf615cb04751c475b9c754240a84bd",
        "name": "Hayden McCabe",
        "sub": false,
        "num_played": 3,
        "IPR": 4
      },
      {
        "key": "79d3ec27db9b3c49e0ef71c6253baa94ac456a41",
        "name": "Jesse Mullene",
        "sub": false,
        "num_played": 3,
        "IPR": 3
      },
      {
        "key": "c903d57c25e79232fa83c3bb417fa062404ed063",
        "name": "Josh Hornbaker",
        "sub": false,
        "num_played": 3,
        "IPR": 3
      },
      {
        "key": "84b5c8062274c3952b6113647c5fab24ae74835e",
        "name": "Malcolm Roberts",
        "sub": false,
        "num_played": 3,
        "IPR": 2
      },
      {
        "key": "8793071958c4f731d401b75239d8e5171f6b9464",
        "name": "Matt Bollinger",
        "sub": false,
        "num_played": 3,
        "IPR": 4
      },
      {
        "key": "c33f161f6d9d27d4f01bbbf0b5fce77bea754652",
        "name": "Matt Watts",
        "sub": false,
        "num_played": 3,
        "IPR": 2
      },
      {
        "key": "01d5567496c6c4663cb317b4772e1f0b1598e670",
        "name": "Michael Ulmen",
        "sub": false,
        "num_played": 3,
        "IPR": 3
      }
    ],
    "ready": true,
    "confirmed": {
      "by": "Claire Burke",
      "at": 1568087529824
    }
  },
  "home": {
    "name": "Seacorns",
    "key": "SCN",
    "captains": [
      {
        "key": "3534d6fb659e3949533cd6cf1dc69941fa7a52e2",
        "name": "Claire Burke"
      },
      {
        "key": "36947e2a22c9f158b9fbfe7ceb6a29d6aa7501ad",
        "name": "Bryn Bomar"
      }
    ],
    "lineup": [
      {
        "key": "89966ef11df0900239ffe459e4c1cdf7c88be6f4",
        "name": "Aaron Donny-Clark",
        "sub": false,
        "num_played": 3,
        "IPR": 1
      },
      {
        "key": "36947e2a22c9f158b9fbfe7ceb6a29d6aa7501ad",
        "name": "Bryn Bomar",
        "sub": false,
        "num_played": 3,
        "IPR": 1
      },
      {
        "key": "3534d6fb659e3949533cd6cf1dc69941fa7a52e2",
        "name": "Claire Burke",
        "sub": false,
        "num_played": 3,
        "IPR": 3
      },
      {
        "key": "8af28a9e189af13127c9722989bd5eb8c38106e3",
        "name": "Danielle Crowson",
        "sub": false,
        "num_played": 3,
        "IPR": 2
      },
      {
        "key": "6ece0245ffb9b778258cd713fe2a5088db8740e1",
        "name": "David Palen",
        "sub": false,
        "num_played": 3,
        "IPR": 2
      },
      {
        "key": "f34bd3d9b939527bc51bd4a8a023ef3f5797f29d",
        "name": "MK Walker",
        "sub": false,
        "num_played": 3,
        "IPR": 3
      },
      {
        "key": "d3b7bbef9f238de4296413bfb999e64b506e328d",
        "name": "Matt Golden",
        "sub": false,
        "num_played": 3,
        "IPR": 4
      },
      {
        "key": "5ae9116cce4386a478f945316dadc934c87191a9",
        "name": "Maureen Hendrix",
        "sub": true,
        "IPR": 5,
        "num_played": 3
      },
      {
        "key": "8f58842092bad71691ff9fe9f18cae273598098c",
        "name": "Nic Crowson",
        "sub": false,
        "num_played": 3,
        "IPR": 5
      },
      {
        "key": "07e4b790cffdc2fbad9cc4a917d11130ae1db967",
        "name": "Sarah Ledray",
        "sub": false,
        "num_played": 3,
        "IPR": 1
      }
    ],
    "ready": true,
    "confirmed": {
      "by": "Hayden McCabe",
      "at": 1568087786063
    }
  },
  "rounds": [
    {
      "n": 1,
      "games": [
        {
          "n": 1,
          "machine": "WhoDunnit",
          "player_1": "98326b585dcf615cb04751c475b9c754240a84bd",
          "player_3": "84b5c8062274c3952b6113647c5fab24ae74835e",
          "player_2": "6ece0245ffb9b778258cd713fe2a5088db8740e1",
          "player_4": "8af28a9e189af13127c9722989bd5eb8c38106e3",
          "done": true,
          "photos": [
            {
              "uploaded_by": "98326b585dcf615cb04751c475b9c754240a84bd",
              "url": "/pics/d0edda6802e1db1c94f6ef4541315cedc43f5d4c",
              "rot": 180,
              "scale": 1.7796970251005102,
              "dx": -198,
              "dy": -109
            }
          ],
          "score_1": 696201660,
          "score_2": 1530667520,
          "score_3": 141755190,
          "score_4": 1073315040,
          "points_1": 0,
          "points_2": 2.5,
          "points_3": 0,
          "points_4": 2.5,
          "score_13": 837956850,
          "score_24": 2603982560,
          "points_13": 0,
          "points_24": 5,
          "away_points": 0,
          "home_points": 5
        },
        {
          "n": 2,
          "machine": "StarWarsE1",
          "player_1": "01d5567496c6c4663cb317b4772e1f0b1598e670",
          "player_3": "79d3ec27db9b3c49e0ef71c6253baa94ac456a41",
          "player_2": "8f58842092bad71691ff9fe9f18cae273598098c",
          "player_4": "36947e2a22c9f158b9fbfe7ceb6a29d6aa7501ad",
          "done": true,
          "photos": [
            {
              "uploaded_by": "3534d6fb659e3949533cd6cf1dc69941fa7a52e2",
              "url": "/pics/4065ac4ef7e26d4b36bea87a984e0a1d8d4e2c8f",
              "rot": 90,
              "scale": 2.6014188867239714,
              "dx": -58,
              "dy": -202
            }
          ],
          "score_1": 87626900,
          "score_2": 113132640,
          "score_3": 70996780,
          "score_4": 53829160,
          "points_1": 1,
          "points_2": 2.5,
          "points_3": 1,
          "points_4": 0.5,
          "score_13": 158623680,
          "score_24": 166961800,
          "points_13": 2,
          "points_24": 3,
          "away_points": 2,
          "home_points": 3
        },
        {
          "n": 3,
          "machine": "Tron",
          "player_1": "c33f161f6d9d27d4f01bbbf0b5fce77bea754652",
          "player_3": "7ee8412002913a652b06f39c31474dcf2c18cdf6",
          "player_2": "07e4b790cffdc2fbad9cc4a917d11130ae1db967",
          "player_4": "5ae9116cce4386a478f945316dadc934c87191a9",
          "photos": [
            {
              "uploaded_by": "7ee8412002913a652b06f39c31474dcf2c18cdf6",
              "url": "/pics/099e0477c6be8b8c4f28417d4dd952013efdf4b7",
              "rot": 0,
              "scale": 1,
              "dx": 0,
              "dy": 0
            }
          ],
          "score_1": 24379870,
          "score_2": 10466030,
          "score_3": 15534000,
          "score_4": 6389200,
          "done": true,
          "points_1": 2.5,
          "points_2": 0,
          "points_3": 2.5,
          "points_4": 0,
          "score_13": 39913870,
          "score_24": 16855230,
          "points_13": 5,
          "points_24": 0,
          "away_points": 5,
          "home_points": 0
        },
        {
          "n": 4,
          "machine": "RollerGames",
          "player_1": "c903d57c25e79232fa83c3bb417fa062404ed063",
          "player_3": "ace784f327f66c086f5246dbb25e7f2eed9a0c68",
          "player_2": "f34bd3d9b939527bc51bd4a8a023ef3f5797f29d",
          "player_4": "d3b7bbef9f238de4296413bfb999e64b506e328d",
          "done": true,
          "photos": [
            {
              "uploaded_by": "c903d57c25e79232fa83c3bb417fa062404ed063",
              "url": "/pics/28b422b64677a5f4296070b96c9d80f8683412c1",
              "rot": 90,
              "scale": 1.8701370219783697,
              "dx": 35,
              "dy": -272
            }
          ],
          "score_1": 11602750,
          "score_2": 2051280,
          "score_3": 18383240,
          "score_4": 1013200,
          "points_1": 2.5,
          "points_2": 0,
          "points_3": 2.5,
          "points_4": 0,
          "score_13": 29985990,
          "score_24": 3064480,
          "points_13": 5,
          "points_24": 0,
          "away_points": 5,
          "home_points": 0
        }
      ],
      "done": true,
      "right_confirmed": {
        "by": "Claire Burke",
        "at": 1568091337334
      },
      "left_confirmed": {
        "by": "Hayden McCabe",
        "at": 1568091441466
      }
    },
    {
      "n": 2,
      "games": [
        {
          "n": 1,
          "machine": "RFM",
          "player_1": "8af28a9e189af13127c9722989bd5eb8c38106e3",
          "player_2": "84b5c8062274c3952b6113647c5fab24ae74835e",
          "done": true,
          "photos": [
            {
              "uploaded_by": "84b5c8062274c3952b6113647c5fab24ae74835e",
              "url": "/pics/514149805d9e8961e778d095b114f33159c8719e",
              "rot": 0,
              "scale": 1,
              "dx": 0,
              "dy": 0
            }
          ],
          "score_1": 47529140,
          "score_2": 95983460,
          "points_1": 0,
          "points_2": 3,
          "points_13": 0,
          "points_24": 3,
          "score_13": 47529140,
          "score_24": 95983460,
          "away_points": 3,
          "home_points": 0
        },
        {
          "n": 2,
          "machine": "BDK",
          "player_1": "3534d6fb659e3949533cd6cf1dc69941fa7a52e2",
          "player_2": "79d3ec27db9b3c49e0ef71c6253baa94ac456a41",
          "done": true,
          "photos": [
            {
              "uploaded_by": "3534d6fb659e3949533cd6cf1dc69941fa7a52e2",
              "url": "/pics/8f49155a348f87ad57629c4b3e85a819ecc07ee1",
              "rot": 90,
              "scale": 2.227745619471216,
              "dx": 49,
              "dy": -158
            }
          ],
          "score_1": 44939460,
          "score_2": 3385950,
          "points_1": 3,
          "points_2": 0,
          "points_13": 3,
          "points_24": 0,
          "score_13": 44939460,
          "score_24": 3385950,
          "away_points": 0,
          "home_points": 3
        },
        {
          "n": 3,
          "machine": "Tron",
          "player_1": "5ae9116cce4386a478f945316dadc934c87191a9",
          "player_2": "c33f161f6d9d27d4f01bbbf0b5fce77bea754652",
          "done": true,
          "photos": [
            {
              "uploaded_by": "5ae9116cce4386a478f945316dadc934c87191a9",
              "url": "/pics/0c7d5e472d59eaf9f47fc4d8be3725e6fd102d72",
              "rot": 0,
              "scale": 2.6902925549759846,
              "dx": -33,
              "dy": -566
            }
          ],
          "score_1": 52390600,
          "score_2": 19202910,
          "points_1": 3,
          "points_2": 0,
          "points_13": 3,
          "points_24": 0,
          "score_13": 52390600,
          "score_24": 19202910,
          "away_points": 0,
          "home_points": 3
        },
        {
          "n": 4,
          "machine": "TSPP",
          "player_1": "f34bd3d9b939527bc51bd4a8a023ef3f5797f29d",
          "player_2": "8793071958c4f731d401b75239d8e5171f6b9464",
          "done": true,
          "photos": [
            {
              "uploaded_by": "8793071958c4f731d401b75239d8e5171f6b9464",
              "url": "/pics/cf2590392735bc7f7bf72d54160ad32189bce2cc",
              "rot": 90,
              "scale": 2.2311261849233697,
              "dx": -45,
              "dy": -246
            }
          ],
          "score_1": 3437150,
          "score_2": 7368660,
          "points_1": 0,
          "points_2": 3,
          "points_13": 0,
          "points_24": 3,
          "score_13": 3437150,
          "score_24": 7368660,
          "away_points": 3,
          "home_points": 0
        },
        {
          "n": 5,
          "machine": "GOT",
          "player_1": "89966ef11df0900239ffe459e4c1cdf7c88be6f4",
          "player_2": "14ca720acc6a110a0aede4417bdccbd293700d49",
          "done": true,
          "photos": [
            {
              "uploaded_by": "14ca720acc6a110a0aede4417bdccbd293700d49",
              "url": "/pics/f8a27cee95946169df3bd06e842c026577646591",
              "rot": 90,
              "scale": 2.03155278477814,
              "dx": 50,
              "dy": -80
            }
          ],
          "score_1": 21680410,
          "score_2": 744549970,
          "points_1": 0,
          "points_2": 3,
          "points_13": 0,
          "points_24": 3,
          "score_13": 21680410,
          "score_24": 744549970,
          "away_points": 3,
          "home_points": 0
        },
        {
          "n": 6,
          "machine": "WhoDunnit",
          "player_1": "6ece0245ffb9b778258cd713fe2a5088db8740e1",
          "player_2": "7ee8412002913a652b06f39c31474dcf2c18cdf6",
          "done": true,
          "photos": [
            {
              "uploaded_by": "7ee8412002913a652b06f39c31474dcf2c18cdf6",
              "url": "/pics/17977c975abfd8193741b4ba373afa213b05884f",
              "rot": 0,
              "scale": 2.0241710664271424,
              "dx": 32,
              "dy": -10
            }
          ],
          "score_1": 571243270,
          "score_2": 1351964510,
          "points_1": 0,
          "points_2": 3,
          "points_13": 0,
          "points_24": 3,
          "score_13": 571243270,
          "score_24": 1351964510,
          "away_points": 3,
          "home_points": 0
        },
        {
          "n": 7,
          "machine": "RollerGames",
          "player_1": "36947e2a22c9f158b9fbfe7ceb6a29d6aa7501ad",
          "player_2": "ace784f327f66c086f5246dbb25e7f2eed9a0c68",
          "photos": [
            {
              "uploaded_by": "36947e2a22c9f158b9fbfe7ceb6a29d6aa7501ad",
              "url": "/pics/d1b2dd8831b6497a51b3a2d8a1cadf251ee81d6c",
              "rot": 0,
              "scale": 5.847324858078615,
              "dx": -482,
              "dy": -226
            }
          ],
          "score_1": 4033260,
          "score_2": 1850090,
          "done": true,
          "points_1": 3,
          "points_2": 0,
          "points_13": 3,
          "points_24": 0,
          "score_13": 4033260,
          "score_24": 1850090,
          "away_points": 0,
          "home_points": 3
        }
      ],
      "done": true,
      "left_confirmed": {
        "by": "Claire Burke",
        "at": 1568093421776
      },
      "right_confirmed": {
        "by": "Clayton Stetz",
        "at": 1568093461064
      }
    },
    {
      "n": 3,
      "games": [
        {
          "n": 1,
          "machine": "TSPP",
          "player_1": "8793071958c4f731d401b75239d8e5171f6b9464",
          "player_2": "89966ef11df0900239ffe459e4c1cdf7c88be6f4",
          "done": true,
          "photos": [
            {
              "uploaded_by": "8793071958c4f731d401b75239d8e5171f6b9464",
              "url": "/pics/a19ea3b8dd7e8863637c5a2ad93ac97d0f9ec8f8",
              "rot": 90,
              "scale": 2.1568985919153207,
              "dx": -18,
              "dy": -328
            }
          ],
          "score_1": 26959890,
          "score_2": 18947940,
          "points_1": 2,
          "points_2": 1,
          "points_13": 2,
          "points_24": 1,
          "score_13": 26959890,
          "score_24": 18947940,
          "away_points": 2,
          "home_points": 1
        },
        {
          "n": 2,
          "machine": "GOT",
          "player_1": "14ca720acc6a110a0aede4417bdccbd293700d49",
          "player_2": "36947e2a22c9f158b9fbfe7ceb6a29d6aa7501ad",
          "done": true,
          "photos": [
            {
              "uploaded_by": "14ca720acc6a110a0aede4417bdccbd293700d49",
              "url": "/pics/7e0a9eb035f998d2d402da8cf0ad9f4ed14b7d46",
              "rot": 90,
              "scale": 2.6667257243630766,
              "dx": 70,
              "dy": -262
            }
          ],
          "score_1": 3257266610,
          "score_2": 62851880,
          "points_1": 3,
          "points_2": 0,
          "points_13": 3,
          "points_24": 0,
          "score_13": 3257266610,
          "score_24": 62851880,
          "away_points": 3,
          "home_points": 0
        },
        {
          "n": 3,
          "machine": "Tron",
          "player_1": "c33f161f6d9d27d4f01bbbf0b5fce77bea754652",
          "player_2": "d3b7bbef9f238de4296413bfb999e64b506e328d",
          "done": true,
          "photos": [
            {
              "uploaded_by": "3534d6fb659e3949533cd6cf1dc69941fa7a52e2",
              "url": "/pics/948666c99efcd7cd285db31a4345c6ec25dcd63e",
              "rot": 0,
              "scale": 2.5102273473310315,
              "dx": 29,
              "dy": -237
            }
          ],
          "score_1": 5808350,
          "score_2": 29331770,
          "points_1": 0,
          "points_2": 3,
          "points_13": 0,
          "points_24": 3,
          "score_13": 5808350,
          "score_24": 29331770,
          "away_points": 0,
          "home_points": 3
        },
        {
          "n": 4,
          "machine": "RollerGames",
          "player_1": "c903d57c25e79232fa83c3bb417fa062404ed063",
          "player_2": "3534d6fb659e3949533cd6cf1dc69941fa7a52e2",
          "done": true,
          "photos": [
            {
              "uploaded_by": "c903d57c25e79232fa83c3bb417fa062404ed063",
              "url": "/pics/c9beb30bf7a5f364aa5d11f0c7343cd26c1739dd",
              "rot": 0,
              "scale": 1.5816766087113188,
              "dx": -1,
              "dy": -130
            }
          ],
          "score_1": 3983330,
          "score_2": 1204180,
          "points_1": 3,
          "points_2": 0,
          "points_13": 3,
          "points_24": 0,
          "score_13": 3983330,
          "score_24": 1204180,
          "away_points": 3,
          "home_points": 0
        },
        {
          "n": 5,
          "machine": "StarWarsE1",
          "player_1": "01d5567496c6c4663cb317b4772e1f0b1598e670",
          "player_2": "8f58842092bad71691ff9fe9f18cae273598098c",
          "done": true,
          "photos": [
            {
              "uploaded_by": "8f58842092bad71691ff9fe9f18cae273598098c",
              "url": "/pics/79b5a61a2ec90f17bfb80701670419abc6df464a",
              "rot": 90,
              "scale": 2.652065266026252,
              "dx": -52,
              "dy": -142
            }
          ],
          "score_1": 27694220,
          "score_2": 61350650,
          "points_1": 0,
          "points_2": 3,
          "points_13": 0,
          "points_24": 3,
          "score_13": 27694220,
          "score_24": 61350650,
          "away_points": 0,
          "home_points": 3
        },
        {
          "n": 6,
          "machine": "WhoDunnit",
          "player_1": "98326b585dcf615cb04751c475b9c754240a84bd",
          "player_2": "07e4b790cffdc2fbad9cc4a917d11130ae1db967",
          "done": true,
          "photos": [
            {
              "uploaded_by": "07e4b790cffdc2fbad9cc4a917d11130ae1db967",
              "url": "/pics/eecfd710181a5db4e8ee94e82ad39b9f4aae5153",
              "rot": 0,
              "scale": 2.409145060338185,
              "dx": -272,
              "dy": -217
            }
          ],
          "score_1": 353180100,
          "score_2": 321124060,
          "points_1": 2,
          "points_2": 1,
          "points_13": 2,
          "points_24": 1,
          "score_13": 353180100,
          "score_24": 321124060,
          "away_points": 2,
          "home_points": 1
        },
        {
          "n": 7,
          "machine": "RFM",
          "player_1": "84b5c8062274c3952b6113647c5fab24ae74835e",
          "player_2": "8af28a9e189af13127c9722989bd5eb8c38106e3",
          "photos": [
            {
              "uploaded_by": "84b5c8062274c3952b6113647c5fab24ae74835e",
              "url": "/pics/5b76ca6d786d52ada85728e4cfe31c092c28208c",
              "rot": 0,
              "scale": 1,
              "dx": 0,
              "dy": 0
            }
          ],
          "score_1": 104235830,
          "score_2": 62292280,
          "done": true,
          "points_1": 2,
          "points_2": 1,
          "points_13": 2,
          "points_24": 1,
          "score_13": 104235830,
          "score_24": 62292280,
          "away_points": 2,
          "home_points": 1
        }
      ],
      "done": true,
      "left_confirmed": {
        "by": "Hayden McCabe",
        "at": 1568096264114
      },
      "right_confirmed": {
        "by": "Claire Burke",
        "at": 1568096277345
      }
    },
    {
      "n": 4,
      "games": [
        {
          "n": 1,
          "machine": "Tron",
          "player_1": "5ae9116cce4386a478f945316dadc934c87191a9",
          "player_3": "07e4b790cffdc2fbad9cc4a917d11130ae1db967",
          "player_2": "7ee8412002913a652b06f39c31474dcf2c18cdf6",
          "player_4": "ace784f327f66c086f5246dbb25e7f2eed9a0c68",
          "photos": [
            {
              "uploaded_by": "5ae9116cce4386a478f945316dadc934c87191a9",
              "url": "/pics/153f35967fe5f34cb2528ebe35bc46bef66383a1",
              "rot": 0,
              "scale": 3.5370630928899005,
              "dx": -125,
              "dy": -837
            }
          ],
          "score_1": 37141810,
          "score_2": 22007230,
          "score_3": 6443860,
          "score_4": 6579930,
          "done": true,
          "points_1": 2.5,
          "points_2": 1,
          "points_3": 0.5,
          "points_4": 1,
          "score_13": 43585670,
          "score_24": 28587160,
          "points_13": 3,
          "points_24": 2,
          "away_points": 2,
          "home_points": 3
        },
        {
          "n": 2,
          "machine": "BDK",
          "player_1": "d3b7bbef9f238de4296413bfb999e64b506e328d",
          "player_3": "3534d6fb659e3949533cd6cf1dc69941fa7a52e2",
          "player_2": "01d5567496c6c4663cb317b4772e1f0b1598e670",
          "player_4": "79d3ec27db9b3c49e0ef71c6253baa94ac456a41",
          "done": true,
          "photos": [
            {
              "uploaded_by": "3534d6fb659e3949533cd6cf1dc69941fa7a52e2",
              "url": "/pics/770f78dc14af73847507e1cae01a509d5a53da22",
              "rot": 90,
              "scale": 4.008117879369467,
              "dx": -139,
              "dy": -311
            }
          ],
          "score_1": 20386290,
          "score_2": 4646150,
          "score_3": 47407890,
          "score_4": 25323190,
          "points_1": 1.5,
          "points_2": 0,
          "points_3": 2.5,
          "points_4": 1,
          "score_13": 67794180,
          "score_24": 29969340,
          "points_13": 4,
          "points_24": 1,
          "away_points": 1,
          "home_points": 4
        },
        {
          "n": 3,
          "machine": "TSPP",
          "player_1": "89966ef11df0900239ffe459e4c1cdf7c88be6f4",
          "player_3": "f34bd3d9b939527bc51bd4a8a023ef3f5797f29d",
          "player_2": "14ca720acc6a110a0aede4417bdccbd293700d49",
          "player_4": "8793071958c4f731d401b75239d8e5171f6b9464",
          "done": true,
          "photos": [
            {
              "uploaded_by": "14ca720acc6a110a0aede4417bdccbd293700d49",
              "url": "/pics/c21cc640819f32afc024eb758d41c723123e6be2",
              "rot": 90,
              "scale": 2.433996125874636,
              "dx": -9,
              "dy": -225
            }
          ],
          "score_1": 6356520,
          "score_2": 72203860,
          "score_3": 3633660,
          "score_4": 10171670,
          "points_1": 0,
          "points_2": 2.5,
          "points_3": 0,
          "points_4": 2.5,
          "score_13": 9990180,
          "score_24": 82375530,
          "points_13": 0,
          "points_24": 5,
          "away_points": 5,
          "home_points": 0
        },
        {
          "n": 4,
          "machine": "RFM",
          "player_1": "8f58842092bad71691ff9fe9f18cae273598098c",
          "player_3": "6ece0245ffb9b778258cd713fe2a5088db8740e1",
          "player_2": "c903d57c25e79232fa83c3bb417fa062404ed063",
          "player_4": "98326b585dcf615cb04751c475b9c754240a84bd",
          "done": true,
          "photos": [
            {
              "uploaded_by": "8f58842092bad71691ff9fe9f18cae273598098c",
              "url": "/pics/747a3f1e31c642700dc3eb906d266c292194cbc9",
              "rot": 90,
              "scale": 2.1673603818665352,
              "dx": 55,
              "dy": -76
            }
          ],
          "score_1": 170612960,
          "score_2": 114634050,
          "score_3": 34016030,
          "score_4": 35013650,
          "points_1": 2.5,
          "points_2": 1,
          "points_3": 0.5,
          "points_4": 1,
          "score_13": 204628990,
          "score_24": 149647700,
          "points_13": 3,
          "points_24": 2,
          "away_points": 2,
          "home_points": 3
        }
      ],
      "done": true,
      "right_confirmed": {
        "by": "Hayden McCabe",
        "at": 1568099860628
      },
      "left_confirmed": {
        "by": "Claire Burke",
        "at": 1568100676315
      }
    }
  ],
  "players": []
}