{
  "key": "mnp-9-5-SJK-DSV",
  "name": "WK5 SJK @ DSV",
  "type": "manual",
  "week": "5",
  "round": 4,
  "create_at": 1520904126906,
  "date": "03/12/2018",
  "state": "complete",
  "venue": {
    "key": "AAB",
    "name": "Add-a-Ball",
    "machines": [
      "AFM",
      "SurfChamp",
      "Indy",
      "EBD",
      "Ghost",
      "TAF",
      "MM",
      "WCS",
      "Nitro",
      "Fathom",
      "Sopranos",
      "TOM",
      "Stars",
      "BM66",
      "BadCats",
      "CFTBL",
      "WhoDunnit",
      "BMX",
      "Whitewater",
      "PlayboyStern"
    ]
  },
  "away": {
    "name": "Soda Jerks",
    "captains": [
      {
        "key": "cbb11d151f5b072c446b5544cfffcda81b4849ad",
        "name": "Bobby Conover"
      },
      {
        "key": "bbab153f8fe19f91ebae16c1a343a982d77d74f1",
        "name": "Raymond Davidson"
      }
    ],
    "lineup": [
      {
        "key": "d4739811f0187b58e528e37ffde835f1e3a2da22",
        "name": "Allison McClure",
        "sub": false,
        "num_played": 3
      },
      {
        "key": "db83a4ca4473a81dba80c8ba2e373372a9170040",
        "name": "Ari Golding",
        "sub": false,
        "num_played": 3
      },
      {
        "key": "65ff360c0605503d17618e5e55d243080beaead2",
        "name": "Austin Arlitt",
        "sub": false,
        "num_played": 3
      },
      {
        "key": "cbb11d151f5b072c446b5544cfffcda81b4849ad",
        "name": "Bobby Conover",
        "sub": false,
        "num_played": 3
      },
      {
        "key": "12c97fbce170d8210570b5f669c1030961f21322",
        "name": "Danny Rashid",
        "sub": false,
        "num_played": 3
      },
      {
        "key": "ff3638d240dd12f06728fc95557574d8e4e6b64b",
        "name": "Jarrett Gaddy",
        "sub": false,
        "num_played": 3
      },
      {
        "key": "231c4e4bb35f8545b18c8a82bebc323ce29e0958",
        "name": "John McAllister",
        "sub": false,
        "num_played": 3
      },
      {
        "key": "096de1fd005e1a9c67479cdf593678ca01bb7df9",
        "name": "Matt Galbraith",
        "sub": false,
        "num_played": 3
      },
      {
        "key": "691e12eb96419ef5ed3c7733152c4097c590cdec",
        "name": "Phil Piwonka",
        "sub": false,
        "num_played": 3
      },
      {
        "key": "bbab153f8fe19f91ebae16c1a343a982d77d74f1",
        "name": "Raymond Davidson",
        "sub": false,
        "num_played": 3
      }
    ],
    "key": "SJK",
    "ready": true,
    "confirmed": {
      "by": "Zac Petersen",
      "at": 1520913213530
    }
  },
  "home": {
    "name": "Death Savers",
    "captains": [
      {
        "key": "80f27879534ce9dc61070ae438d97d1a2940ee7e",
        "name": "Zac Petersen"
      },
      {
        "key": "132e9e2ce9c20f730b7f4cb4d24a0f21521bf342",
        "name": "Lauren Aquino"
      }
    ],
    "lineup": [
      {
        "key": "79126ae755c0b8dab65160f75c3afc8dd108b0aa",
        "name": "Chelsie Hulka",
        "sub": false,
        "num_played": 3
      },
      {
        "key": "9af5bad1f0900f70b25d6ef8ca8b55b5cf47d6af",
        "name": "Dave Stewart",
        "sub": false,
        "num_played": 3
      },
      {
        "key": "bf1f2fb1cea9c857865b7013b22ef334691da53d",
        "name": "Jonathan Hawthorne",
        "sub": false,
        "num_played": 3
      },
      {
        "key": "94cb67cb09f7ffbc43ba487f63f80706c2b9f5c9",
        "name": "Kevin Lessig",
        "sub": false,
        "num_played": 3
      },
      {
        "key": "132e9e2ce9c20f730b7f4cb4d24a0f21521bf342",
        "name": "Lauren Aquino",
        "sub": false,
        "num_played": 3
      },
      {
        "key": "2e4a85dadf699d10ebd31214997263b1af3e5dff",
        "name": "Sarah Hager",
        "sub": false,
        "num_played": 3
      },
      {
        "key": "a3773c7dc4e2b75ee8d9a3b67f34beb43bc391f8",
        "name": "Sherry Smith",
        "sub": false,
        "num_played": 3
      },
      {
        "key": "28509d4e506e6916387382a9db094a4b72dafe5d",
        "name": "Tim McCool",
        "sub": false,
        "num_played": 3
      },
      {
        "key": "2f3c058787195581ea1790c949542da14f2a34ca",
        "name": "Umboon Moore",
        "sub": false,
        "num_played": 3
      },
      {
        "key": "80f27879534ce9dc61070ae438d97d1a2940ee7e",
        "name": "Zac Petersen",
        "sub": false,
        "num_played": 3
      }
    ],
    "key": "DSV",
    "ready": true,
    "confirmed": {
      "by": "Bobby Conover",
      "at": 1520913221631
    }
  },
  "rounds": [
    {
      "n": 1,
      "games": [
        {
          "n": 1,
          "machine": "WhoDunnit",
          "player_1": "db83a4ca4473a81dba80c8ba2e373372a9170040",
          "player_3": "65ff360c0605503d17618e5e55d243080beaead2",
          "player_2": "2f3c058787195581ea1790c949542da14f2a34ca",
          "player_4": "2e4a85dadf699d10ebd31214997263b1af3e5dff",
          "done": true,
          "photos": [
            {
              "uploaded_by": "65ff360c0605503d17618e5e55d243080beaead2",
              "url": "/pics/8727bb9b2ee2e98cd7b4c76fef9197e070754474",
              "rot": 0,
              "scale": 2.9358881187032098,
              "dx": -313,
              "dy": -159
            },
            {
              "uploaded_by": "cbb11d151f5b072c446b5544cfffcda81b4849ad",
              "url": "/pics/d8bffe65d95e457249437b9aabc0f4e689229d23",
              "rot": 0,
              "scale": 1.948554763418446,
              "dx": -182,
              "dy": -293
            }
          ],
          "score_1": 1997834000,
          "score_2": 510770000,
          "score_3": 1430942000,
          "score_4": 590573000,
          "points_1": 2.5,
          "points_2": 0,
          "points_3": 2.5,
          "points_4": 0,
          "score_13": 3428776000,
          "score_24": 1101343000,
          "points_13": 5,
          "points_24": 0,
          "away_points": 5,
          "home_points": 0
        },
        {
          "n": 2,
          "machine": "WCS",
          "player_1": "096de1fd005e1a9c67479cdf593678ca01bb7df9",
          "player_3": "d4739811f0187b58e528e37ffde835f1e3a2da22",
          "player_2": "28509d4e506e6916387382a9db094a4b72dafe5d",
          "player_4": "bf1f2fb1cea9c857865b7013b22ef334691da53d",
          "photos": [
            {
              "uploaded_by": "bf1f2fb1cea9c857865b7013b22ef334691da53d",
              "url": "/pics/d0ad171fb45e7ce4d0f23e187fa87dc0324e8812",
              "rot": 0,
              "scale": 1.548597203431517,
              "dx": -317,
              "dy": -111
            }
          ],
          "done": true,
          "points_1": 0,
          "points_2": 2.5,
          "points_3": 0,
          "points_4": 2.5,
          "points_13": 0,
          "points_24": 5,
          "score_13": 642491840,
          "score_24": 1452782870,
          "score_1": 456711970,
          "score_2": 531069500,
          "score_3": 185779870,
          "score_4": 921713370,
          "away_points": 0,
          "home_points": 5
        },
        {
          "n": 3,
          "machine": "Whitewater",
          "player_1": "cbb11d151f5b072c446b5544cfffcda81b4849ad",
          "player_3": "bbab153f8fe19f91ebae16c1a343a982d77d74f1",
          "player_2": "132e9e2ce9c20f730b7f4cb4d24a0f21521bf342",
          "player_4": "9af5bad1f0900f70b25d6ef8ca8b55b5cf47d6af",
          "done": true,
          "photos": [
            {
              "uploaded_by": "cbb11d151f5b072c446b5544cfffcda81b4849ad",
              "url": "/pics/9e22eba66facbc4d3affe713340a334540163906",
              "rot": 0,
              "scale": 1,
              "dx": 0,
              "dy": 0
            }
          ],
          "score_1": 122123760,
          "score_2": 54242440,
          "score_3": 392606250,
          "score_4": 116234260,
          "points_1": 2.5,
          "points_2": 0,
          "points_3": 2.5,
          "points_4": 0,
          "score_13": 514730010,
          "score_24": 170476700,
          "points_13": 5,
          "points_24": 0,
          "away_points": 5,
          "home_points": 0
        },
        {
          "n": 4,
          "machine": "TOM",
          "player_1": "12c97fbce170d8210570b5f669c1030961f21322",
          "player_3": "ff3638d240dd12f06728fc95557574d8e4e6b64b",
          "player_2": "a3773c7dc4e2b75ee8d9a3b67f34beb43bc391f8",
          "player_4": "80f27879534ce9dc61070ae438d97d1a2940ee7e",
          "done": true,
          "photos": [
            {
              "uploaded_by": "80f27879534ce9dc61070ae438d97d1a2940ee7e",
              "url": "/pics/364ca2a5d79dcb6a72bb9e706798c26a935d338d",
              "rot": 0,
              "scale": 1.3183165467971503,
              "dx": -180,
              "dy": -113
            }
          ],
          "score_1": 735002960,
          "score_2": 355627060,
          "score_3": 1436705490,
          "score_4": 749251240,
          "points_1": 1.5,
          "points_2": 0,
          "points_3": 2.5,
          "points_4": 1,
          "score_13": 2171708450,
          "score_24": 1104878300,
          "points_13": 4,
          "points_24": 1,
          "away_points": 4,
          "home_points": 1
        }
      ],
      "done": true,
      "right_confirmed": {
        "by": "Zac Petersen",
        "at": 1520916652887
      },
      "left_confirmed": {
        "by": "Bobby Conover",
        "at": 1520916658556
      }
    },
    {
      "n": 2,
      "games": [
        {
          "n": 1,
          "machine": "CFTBL",
          "player_1": "80f27879534ce9dc61070ae438d97d1a2940ee7e",
          "player_2": "bbab153f8fe19f91ebae16c1a343a982d77d74f1",
          "done": true,
          "photos": [
            {
              "uploaded_by": "80f27879534ce9dc61070ae438d97d1a2940ee7e",
              "url": "/pics/97f14f1a53e7c3c5486dfc9f05bd6b953f7835b6",
              "rot": 0,
              "scale": 1,
              "dx": 0,
              "dy": 0
            }
          ],
          "score_1": 223598390,
          "score_2": 282415920,
          "points_1": 1,
          "points_2": 2,
          "points_13": 1,
          "points_24": 2,
          "score_13": 223598390,
          "score_24": 282415920,
          "away_points": 2,
          "home_points": 1
        },
        {
          "n": 2,
          "machine": "SurfChamp",
          "player_1": "2f3c058787195581ea1790c949542da14f2a34ca",
          "player_2": "691e12eb96419ef5ed3c7733152c4097c590cdec",
          "photos": [
            {
              "uploaded_by": "691e12eb96419ef5ed3c7733152c4097c590cdec",
              "url": "/pics/66940eab7cd81bb52f24ccc23362761a0eaae676",
              "rot": 90,
              "scale": 1.8014347554923713,
              "dx": -2,
              "dy": -114
            }
          ],
          "score_1": 40370,
          "score_2": 35010,
          "done": true,
          "points_1": 2,
          "points_2": 1,
          "points_13": 2,
          "points_24": 1,
          "score_13": 40370,
          "score_24": 35010,
          "away_points": 1,
          "home_points": 2
        },
        {
          "n": 3,
          "machine": "Fathom",
          "player_1": "94cb67cb09f7ffbc43ba487f63f80706c2b9f5c9",
          "player_2": "12c97fbce170d8210570b5f669c1030961f21322",
          "done": true,
          "photos": [
            {
              "uploaded_by": "cbb11d151f5b072c446b5544cfffcda81b4849ad",
              "url": "/pics/1d44bc006bbac2c31810435e04e33ac3c2c5c920",
              "rot": 0,
              "scale": 1.1931116150939822,
              "dx": -34,
              "dy": -42
            }
          ],
          "score_1": 511730,
          "score_2": 1321740,
          "points_1": 0,
          "points_2": 3,
          "points_13": 0,
          "points_24": 3,
          "score_13": 511730,
          "score_24": 1321740,
          "away_points": 3,
          "home_points": 0
        },
        {
          "n": 4,
          "machine": "EBD",
          "player_1": "bf1f2fb1cea9c857865b7013b22ef334691da53d",
          "player_2": "ff3638d240dd12f06728fc95557574d8e4e6b64b",
          "done": true,
          "photos": [
            {
              "uploaded_by": "bf1f2fb1cea9c857865b7013b22ef334691da53d",
              "url": "/pics/3d427b420e1f24f865e028a9bec74da035cbbfb2",
              "rot": 0,
              "scale": 1,
              "dx": -10,
              "dy": 143
            }
          ],
          "points_1": 3,
          "points_2": 0,
          "points_3": 0,
          "points_4": 0,
          "points_13": 3,
          "points_24": 0,
          "score_13": 1778680,
          "score_24": 756740,
          "score_1": 1778680,
          "score_2": 756740,
          "away_points": 0,
          "home_points": 3
        },
        {
          "n": 5,
          "machine": "PlayboyStern",
          "player_1": "79126ae755c0b8dab65160f75c3afc8dd108b0aa",
          "player_2": "096de1fd005e1a9c67479cdf593678ca01bb7df9",
          "done": true,
          "photos": [
            {
              "uploaded_by": "cbb11d151f5b072c446b5544cfffcda81b4849ad",
              "url": "/pics/85311b889ae3f1eec408566e20cd7ba2ad215dae",
              "rot": 0,
              "scale": 1.5838162108953107,
              "dx": -62,
              "dy": -136
            }
          ],
          "score_1": 28715730,
          "score_2": 8690540,
          "points_1": 3,
          "points_2": 0,
          "points_13": 3,
          "points_24": 0,
          "score_13": 28715730,
          "score_24": 8690540,
          "away_points": 0,
          "home_points": 3
        },
        {
          "n": 6,
          "machine": "BMX",
          "player_1": "28509d4e506e6916387382a9db094a4b72dafe5d",
          "player_2": "65ff360c0605503d17618e5e55d243080beaead2",
          "done": true,
          "photos": [
            {
              "uploaded_by": "80f27879534ce9dc61070ae438d97d1a2940ee7e",
              "url": "/pics/b08cc98a55fa7b181af68625e375ea3f4fbb6bfa",
              "rot": 0,
              "scale": 1,
              "dx": -37,
              "dy": -146
            }
          ],
          "score_1": 1475330,
          "score_2": 753920,
          "points_1": 2,
          "points_2": 1,
          "points_13": 2,
          "points_24": 1,
          "score_13": 1475330,
          "score_24": 753920,
          "away_points": 1,
          "home_points": 2
        },
        {
          "n": 7,
          "machine": "Stars",
          "player_1": "132e9e2ce9c20f730b7f4cb4d24a0f21521bf342",
          "player_2": "231c4e4bb35f8545b18c8a82bebc323ce29e0958",
          "done": true,
          "photos": [
            {
              "uploaded_by": "cbb11d151f5b072c446b5544cfffcda81b4849ad",
              "url": "/pics/f047d724668bae84fa807b1811f97fd9d86a8e25",
              "rot": 0,
              "scale": 1.6893721464897515,
              "dx": -70,
              "dy": -357
            }
          ],
          "score_1": 95020,
          "score_2": 331700,
          "points_1": 0,
          "points_2": 3,
          "points_13": 0,
          "points_24": 3,
          "score_13": 95020,
          "score_24": 331700,
          "away_points": 3,
          "home_points": 0
        }
      ],
      "done": true,
      "right_confirmed": {
        "by": "Bobby Conover",
        "at": 1520918534663
      },
      "left_confirmed": {
        "by": "Zac Petersen",
        "at": 1520918541370
      }
    },
    {
      "n": 3,
      "games": [
        {
          "n": 1,
          "machine": "Whitewater",
          "player_1": "cbb11d151f5b072c446b5544cfffcda81b4849ad",
          "player_2": "9af5bad1f0900f70b25d6ef8ca8b55b5cf47d6af",
          "done": true,
          "photos": [
            {
              "uploaded_by": "cbb11d151f5b072c446b5544cfffcda81b4849ad",
              "url": "/pics/39ee51117ae8df7177bd0551dee01d547bfffe14",
              "rot": 0,
              "scale": 1,
              "dx": 0,
              "dy": 0
            }
          ],
          "score_1": 21487200,
          "score_2": 459098870,
          "points_1": 0,
          "points_2": 3,
          "points_13": 0,
          "points_24": 3,
          "score_13": 21487200,
          "score_24": 459098870,
          "away_points": 0,
          "home_points": 3
        },
        {
          "n": 2,
          "machine": "TAF",
          "player_1": "d4739811f0187b58e528e37ffde835f1e3a2da22",
          "player_2": "a3773c7dc4e2b75ee8d9a3b67f34beb43bc391f8",
          "done": true,
          "photos": [
            {
              "uploaded_by": "d4739811f0187b58e528e37ffde835f1e3a2da22",
              "url": "/pics/acb0af5fd2067e1d0fdba30a25c85d805fb0481f",
              "rot": 0,
              "scale": 1,
              "dx": 0,
              "dy": 0
            }
          ],
          "score_1": 97520480,
          "score_2": 22513770,
          "points_1": 3,
          "points_2": 0,
          "points_13": 3,
          "points_24": 0,
          "score_13": 97520480,
          "score_24": 22513770,
          "away_points": 3,
          "home_points": 0
        },
        {
          "n": 3,
          "machine": "WhoDunnit",
          "player_1": "db83a4ca4473a81dba80c8ba2e373372a9170040",
          "player_2": "2e4a85dadf699d10ebd31214997263b1af3e5dff",
          "photos": [
            {
              "uploaded_by": "cbb11d151f5b072c446b5544cfffcda81b4849ad",
              "url": "/pics/02a89b4c267963dd7ae37c2b1c2508a82f8cd12b",
              "rot": 0,
              "scale": 1.965747077190565,
              "dx": -217,
              "dy": -211
            }
          ],
          "score_1": 145732270,
          "score_2": 545233760,
          "done": true,
          "points_1": 0,
          "points_2": 3,
          "points_13": 0,
          "points_24": 3,
          "score_13": 145732270,
          "score_24": 545233760,
          "away_points": 0,
          "home_points": 3
        },
        {
          "n": 4,
          "machine": "Stars",
          "player_1": "231c4e4bb35f8545b18c8a82bebc323ce29e0958",
          "player_2": "79126ae755c0b8dab65160f75c3afc8dd108b0aa",
          "done": true,
          "photos": [
            {
              "uploaded_by": "65ff360c0605503d17618e5e55d243080beaead2",
              "url": "/pics/801b8d9c3cd4ca085d4f4d65c3ce6f6701dc0ad6",
              "rot": 0,
              "scale": 1.345194567144969,
              "dx": -100,
              "dy": -35
            }
          ],
          "score_1": 188350,
          "score_2": 74230,
          "points_1": 3,
          "points_2": 0,
          "points_13": 3,
          "points_24": 0,
          "score_13": 188350,
          "score_24": 74230,
          "away_points": 3,
          "home_points": 0
        },
        {
          "n": 5,
          "machine": "SurfChamp",
          "player_1": "691e12eb96419ef5ed3c7733152c4097c590cdec",
          "player_2": "132e9e2ce9c20f730b7f4cb4d24a0f21521bf342",
          "done": true,
          "photos": [
            {
              "uploaded_by": "132e9e2ce9c20f730b7f4cb4d24a0f21521bf342",
              "url": "/pics/073f57deb9a496ecdb091a1920d245748bcd4098",
              "rot": 0,
              "scale": 1,
              "dx": 0,
              "dy": 0
            }
          ],
          "score_1": 31660,
          "score_2": 51620,
          "points_1": 1,
          "points_2": 2,
          "points_13": 1,
          "points_24": 2,
          "score_13": 31660,
          "score_24": 51620,
          "away_points": 1,
          "home_points": 2
        },
        {
          "n": 6,
          "machine": "TOM",
          "player_1": "12c97fbce170d8210570b5f669c1030961f21322",
          "player_2": "94cb67cb09f7ffbc43ba487f63f80706c2b9f5c9",
          "done": true,
          "photos": [
            {
              "uploaded_by": "cbb11d151f5b072c446b5544cfffcda81b4849ad",
              "url": "/pics/a27112871f06f95593eac90913dd19737e55dc59",
              "rot": 0,
              "scale": 1,
              "dx": 0,
              "dy": 0
            }
          ],
          "score_1": 1215102930,
          "score_2": 620609400,
          "points_1": 2,
          "points_2": 1,
          "points_13": 2,
          "points_24": 1,
          "score_13": 1215102930,
          "score_24": 620609400,
          "away_points": 2,
          "home_points": 1
        },
        {
          "n": 7,
          "machine": "WCS",
          "player_1": "096de1fd005e1a9c67479cdf593678ca01bb7df9",
          "player_2": "bf1f2fb1cea9c857865b7013b22ef334691da53d",
          "done": true,
          "photos": [
            {
              "uploaded_by": "096de1fd005e1a9c67479cdf593678ca01bb7df9",
              "url": "/pics/5b4a28fd2b06af791469033043269feab2c9c451",
              "rot": 0,
              "scale": 2.158431011831529,
              "dx": -304,
              "dy": -215
            }
          ],
          "score_1": 253374750,
          "score_2": 293156460,
          "points_1": 1,
          "points_2": 2,
          "points_13": 1,
          "points_24": 2,
          "score_13": 253374750,
          "score_24": 293156460,
          "away_points": 1,
          "home_points": 2
        }
      ],
      "done": true,
      "right_confirmed": {
        "by": "Zac Petersen",
        "at": 1520920988308
      },
      "left_confirmed": {
        "by": "Bobby Conover",
        "at": 1520920993614
      }
    },
    {
      "n": 4,
      "games": [
        {
          "n": 1,
          "machine": "PlayboyStern",
          "player_1": "79126ae755c0b8dab65160f75c3afc8dd108b0aa",
          "player_3": "94cb67cb09f7ffbc43ba487f63f80706c2b9f5c9",
          "player_2": "cbb11d151f5b072c446b5544cfffcda81b4849ad",
          "player_4": "ff3638d240dd12f06728fc95557574d8e4e6b64b",
          "done": true,
          "photos": [
            {
              "uploaded_by": "cbb11d151f5b072c446b5544cfffcda81b4849ad",
              "url": "/pics/6613ebffab138ad29b17ac31a5b59e4452cdd6cd",
              "rot": 0,
              "scale": 1,
              "dx": 0,
              "dy": 0
            }
          ],
          "score_1": 3164090,
          "score_2": 46770130,
          "score_3": 3960770,
          "score_4": 27104540,
          "points_1": 0,
          "points_2": 2.5,
          "points_3": 0,
          "points_4": 2.5,
          "score_13": 7124860,
          "score_24": 73874670,
          "points_13": 0,
          "points_24": 5,
          "away_points": 5,
          "home_points": 0
        },
        {
          "n": 2,
          "machine": "WCS",
          "player_1": "80f27879534ce9dc61070ae438d97d1a2940ee7e",
          "player_3": "28509d4e506e6916387382a9db094a4b72dafe5d",
          "player_2": "db83a4ca4473a81dba80c8ba2e373372a9170040",
          "player_4": "d4739811f0187b58e528e37ffde835f1e3a2da22",
          "done": true,
          "points_1": 2.5,
          "points_2": 0,
          "points_3": 2.5,
          "points_4": 0,
          "points_13": 5,
          "points_24": 0,
          "score_13": 762906620,
          "score_24": 366667330,
          "photos": [
            {
              "uploaded_by": "cbb11d151f5b072c446b5544cfffcda81b4849ad",
              "url": "/pics/165f73abdddfec883ec6473661c933f146947d32",
              "rot": 0,
              "scale": 1.702760830278619,
              "dx": -179,
              "dy": -187
            }
          ],
          "score_1": 546545280,
          "score_2": 164274370,
          "score_3": 216361340,
          "score_4": 202392960,
          "away_points": 0,
          "home_points": 5
        },
        {
          "n": 3,
          "machine": "SurfChamp",
          "player_1": "2f3c058787195581ea1790c949542da14f2a34ca",
          "player_3": "a3773c7dc4e2b75ee8d9a3b67f34beb43bc391f8",
          "player_2": "bbab153f8fe19f91ebae16c1a343a982d77d74f1",
          "player_4": "691e12eb96419ef5ed3c7733152c4097c590cdec",
          "done": true,
          "photos": [
            {
              "uploaded_by": "cbb11d151f5b072c446b5544cfffcda81b4849ad",
              "url": "/pics/a9341f0fe7683b33efa7a088baacd2548798dabf",
              "rot": -90,
              "scale": 1.198256285834244,
              "dx": -149,
              "dy": -142
            },
            {
              "uploaded_by": "cbb11d151f5b072c446b5544cfffcda81b4849ad",
              "url": "/pics/a9341f0fe7683b33efa7a088baacd2548798dabf",
              "rot": -90,
              "scale": 1.0677621894694973,
              "dx": -73,
              "dy": -100
            }
          ],
          "score_1": 42150,
          "score_2": 101460,
          "score_3": 30240,
          "score_4": 25990,
          "points_1": 1,
          "points_2": 2.5,
          "points_3": 1,
          "points_4": 0.5,
          "score_13": 72390,
          "score_24": 127450,
          "points_13": 2,
          "points_24": 3,
          "away_points": 3,
          "home_points": 2
        },
        {
          "n": 4,
          "machine": "Nitro",
          "player_1": "9af5bad1f0900f70b25d6ef8ca8b55b5cf47d6af",
          "player_3": "2e4a85dadf699d10ebd31214997263b1af3e5dff",
          "player_2": "65ff360c0605503d17618e5e55d243080beaead2",
          "player_4": "231c4e4bb35f8545b18c8a82bebc323ce29e0958",
          "done": true,
          "photos": [
            {
              "uploaded_by": "132e9e2ce9c20f730b7f4cb4d24a0f21521bf342",
              "url": "/pics/81e1ebe717cf019836ade0b65874aedbadef7d77",
              "rot": 0,
              "scale": 1,
              "dx": 0,
              "dy": 0
            }
          ],
          "score_1": 129140,
          "score_2": 66930,
          "score_3": 714520,
          "score_4": 707310,
          "points_1": 1.5,
          "points_2": 0,
          "points_3": 2.5,
          "points_4": 1,
          "score_13": 843660,
          "score_24": 774240,
          "points_13": 4,
          "points_24": 1,
          "away_points": 1,
          "home_points": 4
        }
      ],
      "done": true,
      "left_confirmed": {
        "by": "Zac Petersen",
        "at": 1520923976923
      },
      "right_confirmed": {
        "by": "Bobby Conover",
        "at": 1520924102547
      }
    }
  ],
  "players": []
}